{
  "orders": [
    {
      "id": 1775030491410,
      "date": "2026-04-01T08:01:31.410Z",
      "userId": "еђѓиґ§AJZ0",
      "dishes": [
        {
          "name": "зєўзѓ§йёЎзї…",
          "note": ""
        },
        {
          "name": "й±јй¦™и‚‰дёќ",
          "note": ""
        }
      ]
    },
    {
      "id": 1775030460287,
      "date": "2026-04-01T08:01:00.287Z",
      "userId": "еђѓиґ§5U70",
      "dishes": [
        {
          "name": "зєўзѓ§и‚‰",
          "note": ""
        },
        {
          "name": "зі–й†‹жЋ’йЄЁ",
          "note": ""
        }
      ]
    },
    {
      "id": 1775027597310,
      "date": "2026-04-01T07:13:17.310Z",
      "userId": "еђѓиґ§Y7J0",
      "dishes": [
        {
          "name": "йє»е©†и±†и…ђ",
          "note": ""
        }
      ]
    },
    {
      "id": 1775027563398,
      "date": "2026-04-01T07:12:43.398Z",
      "userId": "еђѓиґ§Y7J0",
      "dishes": [
        {
          "name": "еЏЇд№ђйёЎзї…",
          "note": ""
        }
      ]
    },
    {
      "id": 1775027079865,
      "date": "2026-04-01T07:04:39.865Z",
      "userId": "еђѓиґ§AJZ0",
      "dishes": [
        {
          "name": "е›ћй”…и‚‰",
          "note": ""
        },
        {
          "name": "е°Џз‚’и‚‰",
          "note": ""
        }
      ]
    },
    {
      "id": 1775027046310,
      "date": "2026-04-01T07:04:06.310Z",
      "userId": "ГҐВђВѓГЁВґВ§2702",
      "dishes": [
        {
          "name": "ГҐВЏВЇГ¤В№ВђГ©ВёВЎГ§ВїВ…",
          "note": ""
        },
        {
          "name": "ГҐВ®В«Г¤ВїВќГ©ВёВЎГ¤ВёВЃ",
          "note": ""
        }
      ]
    },
    {
      "id": 1775025547868,
      "date": "2026-04-01T06:39:07.868Z",
      "userId": "еђѓиґ§AJZ0",
      "dishes": [
        {
          "name": "зєўзѓ§и‚‰",
          "note": ""
        },
        {
          "name": "зі–й†‹жЋ’йЄЁ",
          "note": ""
        }
      ]
    },
    {
      "id": 1775025518134,
      "date": "2026-04-01T06:38:38.134Z",
      "userId": "ГҐВђВѓГЁВґВ§2702",
      "dishes": [
        {
          "name": "Г§ВєВўГ§ВѓВ§ГЁВ‚В‰",
          "note": ""
        }
      ]
    },
    {
      "id": 1775025516722,
      "date": "2026-04-01T06:38:36.722Z",
      "userId": "ГҐВђВѓГЁВґВ§2702",
      "dishes": [
        {
          "name": "Г§ВєВўГ§ВѓВ§ГЁВ‚В‰",
          "note": ""
        }
      ]
    },
    {
      "id": 1775022975387,
      "date": "2026-04-01T05:56:15.387Z",
      "userId": "ГҐВђВѓГЁВґВ§2702",
      "dishes": [
        {
          "name": "Г§ВєВўГ§ВѓВ§ГЁВ‚В‰",
          "note": ""
        }
      ]
    }
  ],
  "customDishes": [],
  "deletedDishIds": [],
  "userId": "еђѓиґ§AJZ0"
}